[
  {
    "id": 3,
    "usuario": "ADRIANA SOFIA CARRASCO GARCIA",
    "prestamista": "EDER",
    "equipo": "LAPTOP HP 6",
    "categoria": "Computadora",
    "estado_equipo": "Completo",
    "fecha_prestamo": "2025-09-05 09:11",
    "fecha_entrega": "2025-09-05 10:14",
    "quien_recibe": "EDER",
    "estado": "Entregado",
    "observaciones": "",
    "estado_equipo_entrega": "Completo"
  },
  {
    "id": 4,
    "usuario": "CAMPOS MUNGUIA LORENA ADRIANA",
    "prestamista": "EDER",
    "equipo": "LAPTOP HP 6",
    "categoria": "Computadora",
    "estado_equipo": "Completo",
    "fecha_prestamo": "2025-09-05 10:14",
    "fecha_entrega": null,
    "quien_recibe": "",
    "estado": "Prestado",
    "observaciones": ""
  },
  {
    "id": 5,
    "usuario": "SALAS CASTRO JULIA MINERVA",
    "prestamista": "EDER",
    "equipo": "",
    "controles": "PROYECTOR NEGRO 1",
    "cables": "",
    "audifonos": "",
    "estado_equipo": "Completo",
    "fecha_prestamo": "2025-09-05 11:26",
    "fecha_entrega": null,
    "quien_recibe": "",
    "estado": "Prestado",
    "observaciones": ""
  }
]